morphsync/__init__.py
morphsync/base.py
morphsync/data.py
morphsync/graph.py
morphsync/io.py
morphsync/mapping.py
morphsync/mesh.py
morphsync/morph.py
morphsync/points.py
morphsync/table.py
morphsync-0.2.1.dist-info/METADATA
morphsync-0.2.1.dist-info/WHEEL
morphsync-0.2.1.dist-info/RECORD
