Metadata-Version: 2.4
Name: morphsync
Version: 0.2.1
Summary: A package for managing multilayer morphology data
Project-URL: Repository, https://github.com/bdpedigo/morphsync
Project-URL: Homepage, https://github.com/bdpedigo/morphsync
Project-URL: Documentation, https://bdpedigo.github.io/morphsync/
Project-URL: Issues, https://github.com/bdpedigo/morphsync/issues
Requires-Python: >=3.11
Requires-Dist: cachetools>=5.5.1
Requires-Dist: fastremap>=1.15.1
Requires-Dist: joblib>=1.5.1
Requires-Dist: networkx>=3.5
Requires-Dist: numpy>=2.0.1
Requires-Dist: pandas>=2.3.1
Requires-Dist: pooch>=1.8.2
Requires-Dist: scikit-learn>=1.5.0
Requires-Dist: scipy>=1.15.0
